theswarm/__init__.py
theswarm/__main__.py
theswarm/swarm.py
theswarm-0.1.1.dist-info/LICENSE
theswarm-0.1.1.dist-info/METADATA
theswarm-0.1.1.dist-info/WHEEL
theswarm-0.1.1.dist-info/RECORD
