Metadata-Version: 2.3
Name: theswarm
Version: 0.1.1
Summary: A powerful distributed AI framework for collaborative intelligence and swarm learning
License: MIT
Keywords: ai,swarm-intelligence,distributed-computing,machine-learning
Author: Laurent-Philippe Albou
Author-email: lpalbou@gmail.com
Requires-Python: >=3.8,<4.0
Classifier: Development Status :: 3 - Alpha
Classifier: Intended Audience :: Developers
Classifier: Intended Audience :: Science/Research
Classifier: License :: OSI Approved :: MIT License
Classifier: Programming Language :: Python :: 3
Classifier: Programming Language :: Python :: 3.8
Classifier: Programming Language :: Python :: 3.9
Classifier: Programming Language :: Python :: 3.10
Classifier: Programming Language :: Python :: 3.11
Classifier: Programming Language :: Python :: 3.12
Classifier: Programming Language :: Python :: 3.13
Classifier: Topic :: Scientific/Engineering :: Artificial Intelligence
Provides-Extra: all
Provides-Extra: pytorch
Provides-Extra: tensorflow
Requires-Dist: numpy (>=1.20.0,<2.0.0)
Requires-Dist: tensorflow (>=2.8.0,<3.0.0) ; extra == "tensorflow" or extra == "all"
Requires-Dist: torch (>=1.10.0,<2.0.0) ; extra == "pytorch" or extra == "all"
Project-URL: Homepage, https://github.com/lpalbou/theswarm
Project-URL: Repository, https://github.com/lpalbou/theswarm
